{
    "properties": {
        "roleName": "Custodian-ecc-azure-267-11_asb_java_funcapp",
        "description": "",
        "assignableScopes": [
            "/subscriptions/{subscription_id}"
        ],
        "permissions": [
            {
                "actions": [
                    "Microsoft.Web/sites/Read",
                    "Microsoft.Web/sites/config/Read"
                ],
                "notActions": [],
                "dataActions": [],
                "notDataActions": []
            }
        ]
    }
}